{"cameraMode":{"drawMode":0,"name":"Shaded","section":"Shading Mode"},"sceneLighting":true,"audioPlay":false,"sceneViewState":{"showFog":true,"showMaterialUpdate":false,"showSkybox":true,"showFlares":true,"showImageEffects":true,"showParticleSystems":true},"in2DMode":false,"pivot":{"x":-374.657958984375,"y":-328.49945068359377,"z":-1105.9361572265625},"rotation":{"x":-0.03179571405053139,"y":0.963373064994812,"z":-0.13268519937992097,"w":-0.23085959255695344},"size":1237.054443359375,"orthographic":false}